harvester_curator/__init__.py
harvester_curator/cli.py
harvester_curator/curator/__init__.py
harvester_curator/curator/api_end_points/darus_md_schema_api_endpoints.json
harvester_curator/curator/curator.py
harvester_curator/curator/dataset_upload.py
harvester_curator/curator/mapping.json
harvester_curator/example/use-case/codemeta.json
harvester_curator/example/use-case/install.py
harvester_curator/example/use-case/ned.bib
harvester_curator/example/use-case/requirements.txt
harvester_curator/harvester/__init__.py
harvester_curator/harvester/crawler.py
harvester_curator/harvester/file_group.py
harvester_curator/harvester/harvester.py
harvester_curator/harvester/parser/__init__.py
harvester_curator/harvester/parser/append_value.py
harvester_curator/harvester/parser/parse_bib.py
harvester_curator/harvester/parser/parse_cff.py
harvester_curator/harvester/parser/parse_hdf.py
harvester_curator/harvester/parser/parse_json.py
harvester_curator/harvester/parser/parse_vtk.py
harvester_curator/harvester/parser/parse_yaml.py
harvester_curator/harvester/parser/parser.py
harvester_curator/harvester/parser/utils.py
harvester_curator/requirements.txt
harvester_curator-0.0.3.dist-info/LICENSE.txt
harvester_curator-0.0.3.dist-info/METADATA
harvester_curator-0.0.3.dist-info/WHEEL
harvester_curator-0.0.3.dist-info/entry_points.txt
harvester_curator-0.0.3.dist-info/RECORD
