Metadata-Version: 2.1
Name: harvester-curator
Version: 0.0.3
Summary: A package for harvesting, curating and uploading metadata.
Author: Sarbani Roy
Author-email: sarbani.roy@simtech.uni-stuttgart.de
Requires-Python: >=3.10,<3.13
Classifier: Programming Language :: Python :: 3
Classifier: Programming Language :: Python :: 3.10
Classifier: Programming Language :: Python :: 3.11
Classifier: Programming Language :: Python :: 3.12
Requires-Dist: PyYAML (>=6.0.1,<7.0.0)
Requires-Dist: cffconvert (>=2.0.0,<3.0.0)
Requires-Dist: easyDataverse (>=0.4.0,<0.5.0)
Requires-Dist: h5py (>=3.11.0,<4.0.0)
Requires-Dist: pydantic (>=2.6.1,<3.0.0)
Requires-Dist: python-magic (>=0.4.27,<0.5.0)
Requires-Dist: pyvista (>=0.43.3,<0.44.0)
Requires-Dist: vtk (>=9.3.0,<10.0.0)
